{
  "alpha": null,
  "seed": 42,
  "n_train": 30,
  "n_population": 5000,
  "train_loss": 0.3306107841939083,
  "population_risk": 0.9562604114913714,
  "bayes_population_risk": 0.1214410313285021,
  "empirical_bayes_risk": 0.12092378285564537,
  "generalization_gap": 0.6256496272974631,
  "excess_population_risk": 0.8348193801628693,
  "runtime_seconds": 17.20750466361642,
  "runtime_per_step_seconds": 0.0034415009327232837,
  "initial_objective": 0.576429006873221,
  "final_objective": 0.3503001526249819,
  "best_objective": 0.3503001526249819,
  "objective_reduction": 0.2261288542482391,
  "initial_train_loss_history": 0.5755910349675971,
  "final_train_loss_history": 0.3306107841939083,
  "best_train_loss_history": 0.3306107841939083,
  "train_loss_reduction": 0.2449802507736888,
  "weight_norm": 78.75419381536071,
  "trace_s": 78.7541938153607,
  "top_eigenvalue": 56.00292580547233,
  "min_eigenvalue": 1.3575096549801363e-08,
  "R1": 0.711110394155913,
  "effective_rank": 2.959078271841743,
  "config_suffix": "cov_toeplitz_bump_mask_random_rho_0p7_lambda_1e-05_beta_1_d_25_T_5_lr_0p001_iter_5000_ntrain_30_seed_42",
  "ridge_lambda": 0.01,
  "ridge_train_loss": 0.10825048945172841,
  "ridge_population_risk": 0.1414533285631846,
  "ridge_generalization_gap": 0.03320283911145619,
  "ridge_excess_population_risk": 0.020012297234682494,
  "pca_n_components": 62,
  "pca_train_loss": 2.8005583958998074e-16,
  "pca_population_risk": 0.8731789417161523,
  "pca_generalization_gap": 0.873178941716152,
  "pca_excess_population_risk": 0.7517379103876501
}